markdown_editing/__init__.py
markdown_editing/extension.py
markdown_editing-0.2.0.dist-info/LICENSE
markdown_editing-0.2.0.dist-info/METADATA
markdown_editing-0.2.0.dist-info/WHEEL
markdown_editing-0.2.0.dist-info/top_level.txt
markdown_editing-0.2.0.dist-info/RECORD
