Metadata-Version: 2.1
Name: markdown-editing
Version: 0.2.0
Summary: Markdown extension for editing marks and comments
Home-page: https://github.com/makyo/markdown-editing
Author: Madison Scott-Clary
Author-email: makyo@drab-makyo.com
Classifier: Development Status :: 4 - Beta
Classifier: License :: OSI Approved :: MIT License
Classifier: Operating System :: OS Independent
Classifier: Topic :: Text Processing
Classifier: Programming Language :: Python :: 3
License-File: LICENSE
Requires-Dist: markdown
